pydeepmerge/__init__.py
pydeepmerge/_deep_merge.py
pydeepmerge/_merge_configs.py
pydeepmerge/errors/__init__.py
pydeepmerge/errors/errors.py
pydeepmerge/parsers/__init__.py
pydeepmerge/parsers/_loader.py
pydeepmerge/parsers/json.py
pydeepmerge/parsers/yaml.py
pydeepmerge/strategies/__init__.py
pydeepmerge/strategies/_strategies.py
pydeepmerge/strategies/decorators/__init__.py
pydeepmerge/strategies/decorators/_decorators.py
pydeepmerge/types/__init__.py
pydeepmerge/types/types.py
pydeepmerge-0.3.3.dist-info/LICENSE
pydeepmerge-0.3.3.dist-info/METADATA
pydeepmerge-0.3.3.dist-info/WHEEL
pydeepmerge-0.3.3.dist-info/entry_points.txt
pydeepmerge-0.3.3.dist-info/top_level.txt
pydeepmerge-0.3.3.dist-info/RECORD
