Metadata-Version: 2.1
Name: pydeepmerge
Version: 0.3.3
Summary: A lightweight library to perform deep merges of python dictionaries
Home-page: https://github.com/taliamax/pydeepmerge
Author: Natalia Maximo
Author-email: iam@natalia.dev
License: MIT
Keywords: mapping dictionary library merge
Platform: UNKNOWN
Classifier: Development Status :: 4 - Beta
Classifier: Intended Audience :: Developers
Classifier: License :: OSI Approved :: MIT License
Classifier: Operating System :: OS Independent
Classifier: Programming Language :: Python :: 3
Classifier: Programming Language :: Python :: 3.5
Classifier: Programming Language :: Python :: 3.6
Classifier: Programming Language :: Python :: 3.7
Classifier: Programming Language :: Python :: 3.8
Classifier: Topic :: Software Development :: Libraries
Classifier: Topic :: Software Development :: Libraries :: Python Modules
Requires-Python: >=3.5
Provides-Extra: test
Requires-Dist: pytest ; extra == 'test'
Requires-Dist: pytest-cov ; extra == 'test'
Requires-Dist: coveralls ; extra == 'test'
Requires-Dist: flake8 ; extra == 'test'
Provides-Extra: yaml
Requires-Dist: pyyaml ; extra == 'yaml'
